stackexchange_question_analyzer/__init__.py
stackexchange_question_analyzer/main.py
stackexchange_question_analyzer/prompts.py
stackexchange_question_analyzer-2025.12.21142930.dist-info/METADATA
stackexchange_question_analyzer-2025.12.21142930.dist-info/WHEEL
stackexchange_question_analyzer-2025.12.21142930.dist-info/top_level.txt
stackexchange_question_analyzer-2025.12.21142930.dist-info/RECORD
