Metadata-Version: 2.4
Name: stackexchange-question-analyzer
Version: 2025.12.21142930
Summary: The package aims to provide a structured analysis of user-generated content on platforms like Stack Exchange by determining the monthly volume of questions asked. This is useful for understanding comm
Author-email: stackexchange-question-analyzer <hi@eugene.plus>
License: MIT
Project-URL: Homepage, https://github.com/chigwell/stackexchange-question-analyzer
Requires-Python: >=3.9
Requires-Dist: langchain-llm7>=0.0.0
Requires-Dist: llmatch-messages>=0.0.0
Requires-Dist: langchain-core>=0.3.0
